uri_handler/__init__.py
uri_handler/errors.py
uri_handler/handle_uris.py
uri_handler/uri_functions.py
uri_handler/storage/__init__.py
uri_handler/storage/filestorage.py
uri_handler/storage/marsh.py
uri_handler/storage/s3storage.py
uri_handler/utils/__init__.py
uri_handler/utils/_compat.py
uri_handler/utils/uri_utils.py
uri_handler-0.0.4.dist-info/METADATA
uri_handler-0.0.4.dist-info/WHEEL
uri_handler-0.0.4.dist-info/top_level.txt
uri_handler-0.0.4.dist-info/RECORD
