Metadata-Version: 2.1
Name: uri-handler
Version: 0.0.4
Summary: standardized operations on s3 and file uris
Home-page: https://github.com/RussTorres/uri_handler
Author: Russel Torres
Author-email: russelt@alleninstitute.org
License: UNKNOWN
Platform: UNKNOWN
Requires-Dist: atomicwrites
Requires-Dist: boto3
Requires-Dist: decorator
Requires-Dist: marshmallow
Requires-Dist: six
Requires-Dist: pathlib2 ; python_version < "3.0"
